fluxai/__init__.py
fluxai-0.0.1.dist-info/METADATA
fluxai-0.0.1.dist-info/WHEEL
fluxai-0.0.1.dist-info/licenses/LICENSE
fluxai-0.0.1.dist-info/RECORD
